LICENSE
MANIFEST.in
README.rst
pyproject.toml
setup.cfg
setup.py
eo_tilematcher/__init__.py
eo_tilematcher/__main__.py
eo_tilematcher.egg-info/PKG-INFO
eo_tilematcher.egg-info/SOURCES.txt
eo_tilematcher.egg-info/dependency_links.txt
eo_tilematcher.egg-info/entry_points.txt
eo_tilematcher.egg-info/requires.txt
eo_tilematcher.egg-info/top_level.txt
eo_tilematcher/data/data_builder.py
eo_tilematcher/data/ezequiel-ramos-mexia-dam.geojson
eo_tilematcher/data/fontana-lake.geojson
eo_tilematcher/data/landsat/WRS2_descending_0.zip
eo_tilematcher/data/landsat/landsat_tiles.cpg
eo_tilematcher/data/landsat/landsat_tiles.dbf
eo_tilematcher/data/landsat/landsat_tiles.prj
eo_tilematcher/data/landsat/landsat_tiles.shp
eo_tilematcher/data/landsat/landsat_tiles.shx
eo_tilematcher/data/sentinel2/sentinel2_tiles.cpg
eo_tilematcher/data/sentinel2/sentinel2_tiles.dbf
eo_tilematcher/data/sentinel2/sentinel2_tiles.prj
eo_tilematcher/data/sentinel2/sentinel2_tiles.shp
eo_tilematcher/data/sentinel2/sentinel2_tiles.shx
eo_tilematcher/data/sentinel2/sentinel2_tiles_world.zip
eo_tilematcher/tests/__init__.py
eo_tilematcher/tests/test_eo_tilematcher.py
examples/eo-tilematcher-101.ipynb
examples/test.py