Metadata-Version: 2.1
Name: eo-tilematcher
Version: 0.1.1
Summary: Tools to quickly find the Sentinel2, Landasat5, and Landsat8 tiles that match a given region of interest.
Home-page: https://github.com/EO-Forge/eo_tilematcher.git
Author: Felix Rojo Lapalma, Andrés Pérez Hortal
License: UNKNOWN
Platform: UNKNOWN
Classifier: Development Status :: 4 - Beta
Classifier: License :: OSI Approved :: MIT License
Classifier: Programming Language :: Python :: 3
Classifier: Operating System :: OS Independent
Requires-Python: >=3.7
License-File: LICENSE
